download_tiles/__init__.py
download_tiles/cli.py
download_tiles-0.4.1.dist-info/LICENSE
download_tiles-0.4.1.dist-info/METADATA
download_tiles-0.4.1.dist-info/WHEEL
download_tiles-0.4.1.dist-info/entry_points.txt
download_tiles-0.4.1.dist-info/top_level.txt
download_tiles-0.4.1.dist-info/RECORD
