Metadata-Version: 2.1
Name: download-tiles
Version: 0.4.1
Summary: Download map tiles and store them in an MBTiles database
Home-page: https://github.com/simonw/download-tiles
Author: Simon Willison
License: Apache License, Version 2.0
Project-URL: Issues, https://github.com/simonw/download-tiles/issues
Project-URL: CI, https://github.com/simonw/download-tiles/actions
Project-URL: Changelog, https://github.com/simonw/download-tiles/releases
Platform: UNKNOWN
Requires-Python: >=3.6
Requires-Dist: click
Requires-Dist: requests
Requires-Dist: landez (==2.5.0)
Provides-Extra: test
Requires-Dist: pytest ; extra == 'test'
Requires-Dist: requests-mock ; extra == 'test'
